<?xml version="1.0" encoding="utf-8"?>
<Containers>
<Plugin>True</Plugin>
<PluginURL>https://raw.githubusercontent.com/desertwitch/mirrorshuttle-unRAID/main/plugin/mirsht.plg</PluginURL>
<PluginAuthor>desertwitch (Rysz)</PluginAuthor>
<Beta>True</Beta>
<Category>Tools: Tools:System</Category>
<Name>MirrorShuttle for UNRAID</Name>
<Description>
MirrorShuttle helps to achieve a very specific security and anti-ransomware oriented workflow for your media server. The tool mirrors the folder structure of your read-only shares into your incoming area, so you can organise files within that mirror structure. MirrorShuttle then moves new content from that structure to the pre-planned locations in the read-only shares, without opening these shares to writes.
</Description>
<Support>https://forums.unraid.net/topic/191119-plugin-mirrorshuttle-for-unraid/</Support>
<Icon>https://raw.githubusercontent.com/desertwitch/mirrorshuttle-unRAID/main/plugin/mirsht.png</Icon>
<Date>2025-06-12</Date>
<Changes>
###2025.06.12d
- release note: welcome to the first version of the MirrorShuttle package.
- release note: please report any problems in the support topic.
</Changes>
</Containers>
